immutable_collection/__init__.py
immutable_collection/collection.py
immutable_collection/collection_test.py
immutable_collection-1.1.post2.dist-info/METADATA
immutable_collection-1.1.post2.dist-info/RECORD
immutable_collection-1.1.post2.dist-info/WHEEL
immutable_collection-1.1.post2.dist-info/top_level.txt
